pkvid/__init__.py
pkvid/__main__.py
pkvid/blender.py
pkvid/cli.py
pkvid/config.py
pkvid/project.py
pkvid-0.1.0.dist-info/METADATA
pkvid-0.1.0.dist-info/WHEEL
pkvid-0.1.0.dist-info/RECORD
